pixtract/__init__.py
pixtract/__main__.py
pixtract/cli.py
pixtract/main.py
pixtract/processing.py
pixtract/utils.py
pixtract-0.1.0.dist-info/licenses/LICENSE
pixtract-0.1.0.dist-info/METADATA
pixtract-0.1.0.dist-info/WHEEL
pixtract-0.1.0.dist-info/entry_points.txt
pixtract-0.1.0.dist-info/top_level.txt
pixtract-0.1.0.dist-info/RECORD
