Metadata-Version: 2.4
Name: pixtract
Version: 0.1.0
Summary: A command-line tool to extract high-quality frames from videos.
Author-email: Rahatul Islam <rahatulghazi@gmail.com>
License: MIT License
Classifier: Programming Language :: Python :: 3
Classifier: Operating System :: OS Independent
Requires-Python: >=3.8
License-File: LICENSE
Requires-Dist: opencv-python
Requires-Dist: scikit-image
Requires-Dist: tqdm
Requires-Dist: colorama
Provides-Extra: dev
Requires-Dist: ruff; extra == "dev"
Requires-Dist: pytest; extra == "dev"
Dynamic: license-file
